loguru_throttler/__init__.py
loguru_throttler/throttler.py
tests/__init__.py
tests/test_throttler.py
loguru_throttler-0.2.3.dist-info/LICENSE
loguru_throttler-0.2.3.dist-info/METADATA
loguru_throttler-0.2.3.dist-info/WHEEL
loguru_throttler-0.2.3.dist-info/top_level.txt
loguru_throttler-0.2.3.dist-info/RECORD
