Metadata-Version: 2.2
Name: loguru-throttler
Version: 0.2.3
Summary: A package for throttling duplicate log messages in loguru
Home-page: https://github.com/yourusername/loguru-throttler
Author: Author
Author-email: Chuck Melanson <chuck@acadiancapitalpartners.com>
License: MIT License
Project-URL: Homepage, https://github.com/acadiancapitalpartners/loguru-throttler
Project-URL: Bug Tracker, https://github.com/acadiancapitalpartners/loguru-throttler/issues
Keywords: loguru,logging,throttling
Classifier: Programming Language :: Python :: 3
Classifier: License :: OSI Approved :: MIT License
Classifier: Operating System :: OS Independent
Requires-Python: >=3.7
License-File: LICENSE
Requires-Dist: loguru>=0.6.0
Dynamic: author
Dynamic: home-page
Dynamic: requires-python
